{
    "bridge": {
        "benchmarks": {
            "regexp": {
                "engines": {
                    "d8+pypy": {
                        "max": 863.7713004484306, 
                        "mean": 506.01827411167505, 
                        "min": 375.89729729729726
                    }, 
                    "d8+pypy-nojit": {
                        "max": 357.73275862068965, 
                        "mean": 398.0985365853659, 
                        "min": 432.35294117647055
                    }, 
                    "js+pypy": {
                        "max": 81.34408602150538, 
                        "mean": 98.54321728691477, 
                        "min": 92.94516129032257
                    }, 
                    "js+pypy-nojit": {
                        "max": 83.26271186440678, 
                        "mean": 95.51789976133651, 
                        "min": 81.48101265822785
                    }
                }, 
                "machine": "922174a8388e0a2f", 
                "platform": "darwin", 
                "timestamp": "20150314070531"
            }, 
            "sumlog": {
                "engines": {
                    "d8+pypy": {
                        "max": 556.4687475562499, 
                        "mean": 601.2799994146666, 
                        "min": 596.1739187652174
                    }, 
                    "d8+pypy-nojit": {
                        "max": 605.6363654848484, 
                        "mean": 722.2469117901235, 
                        "min": 807.6249957083334
                    }, 
                    "js+pypy": {
                        "max": 196.84210576526317, 
                        "mean": 233.95348704139536, 
                        "min": 210.92857633285715
                    }, 
                    "js+pypy-nojit": {
                        "max": 273.5555569333333, 
                        "mean": 325.95237663809525, 
                        "min": 320.9999891430769
                    }
                }, 
                "machine": "922174a8388e0a2f", 
                "platform": "darwin", 
                "timestamp": "20150314070531"
            }
        }, 
        "geometric_mean": {
            "engines": {
                "d8+pypy": {
                    "max": 693.2977237345955, 
                    "mean": 551.5964716726155, 
                    "min": 473.39218918670775
                }, 
                "d8+pypy-nojit": {
                    "max": 465.4631754993117, 
                    "mean": 536.2139858647366, 
                    "min": 590.9137350427153
                }, 
                "js+pypy": {
                    "max": 126.53829927742757, 
                    "mean": 151.8371802575101, 
                    "min": 140.01710805467854
                }, 
                "js+pypy-nojit": {
                    "max": 150.9204343879498, 
                    "mean": 176.4491043861855, 
                    "min": 161.7263249401842
                }
            }, 
            "machine": "922174a8388e0a2f", 
            "platform": "darwin", 
            "timestamp": "20150314070531"
        }
    }, 
    "machine": "922174a8388e0a2f", 
    "misc": {
        "benchmarks": {
            "file_size_gz": {
                "engines": {
                    "pypy": {
                        "max": 4146022, 
                        "mean": 4146022.0, 
                        "min": 4146022
                    }, 
                    "pypy-nojit": {
                        "max": 2557788, 
                        "mean": 2557788.0, 
                        "min": 2557788
                    }
                }, 
                "machine": "922174a8388e0a2f", 
                "platform": "darwin", 
                "timestamp": "20150113203542"
            }, 
            "file_size_raw": {
                "engines": {
                    "pypy": {
                        "max": 22067048, 
                        "mean": 22067048.0, 
                        "min": 22067048
                    }, 
                    "pypy-nojit": {
                        "max": 13638890, 
                        "mean": 13638890.0, 
                        "min": 13638890
                    }
                }, 
                "machine": "922174a8388e0a2f", 
                "platform": "darwin", 
                "timestamp": "20150113203542"
            }, 
            "load_time": {
                "engines": {
                    "d8+pypy": {
                        "max": 2.061, 
                        "mean": 2.026, 
                        "min": 2.026
                    }, 
                    "d8+pypy-nojit": {
                        "max": 1.465, 
                        "mean": 1.451, 
                        "min": 1.451
                    }, 
                    "js+pypy": {
                        "max": 2.908, 
                        "mean": 2.665, 
                        "min": 2.665
                    }, 
                    "js+pypy-nojit": {
                        "max": 1.841, 
                        "mean": 1.786, 
                        "min": 1.786
                    }
                }, 
                "machine": "922174a8388e0a2f", 
                "platform": "darwin", 
                "timestamp": "20150113203542"
            }, 
            "pystone": {
                "engines": {
                    "cpython": {
                        "max": 134673.967791, 
                        "mean": 123812.68585650001, 
                        "min": 114293.551558
                    }, 
                    "d8+pypy": {
                        "max": 675674.578499, 
                        "mean": 414743.9262118501, 
                        "min": 17205.781741
                    }, 
                    "d8+pypy-nojit": {
                        "max": 12722.6468662, 
                        "mean": 11495.750589094001, 
                        "min": 7498.50031924
                    }, 
                    "js+pypy": {
                        "max": 467289.228171, 
                        "mean": 373909.09059707995, 
                        "min": 80385.8548015
                    }, 
                    "js+pypy-nojit": {
                        "max": 39215.6760081, 
                        "mean": 37122.10644791, 
                        "min": 36153.2864093
                    }, 
                    "pypy": {
                        "max": 3627663.03408, 
                        "mean": 2699563.3649635, 
                        "min": 929939.028446
                    }, 
                    "pypy-nojit": {
                        "max": 75441.1928701, 
                        "mean": 69311.55150606002, 
                        "min": 67756.7486097
                    }
                }, 
                "machine": "922174a8388e0a2f", 
                "platform": "darwin", 
                "timestamp": "20150113203542"
            }
        }
    }, 
    "platform": "darwin", 
    "py": {
        "benchmarks": {
            "chaos": {
                "engines": {
                    "cpython": {
                        "max": 0.43784403801, 
                        "mean": 0.27716372013075, 
                        "min": 0.252552986145
                    }, 
                    "d8+pypy": {
                        "max": 2.78200006485, 
                        "mean": 0.3385499954219349, 
                        "min": 0.0390000343323
                    }, 
                    "d8+pypy-nojit": {
                        "max": 1.84800004959, 
                        "mean": 1.5068500041954995, 
                        "min": 1.42000007629
                    }, 
                    "js+pypy": {
                        "max": 0.655999898911, 
                        "mean": 0.12309999465938001, 
                        "min": 0.0590000152588
                    }, 
                    "js+pypy-nojit": {
                        "max": 0.959000110626, 
                        "mean": 0.6789499998092999, 
                        "min": 0.635000228882
                    }, 
                    "pypy": {
                        "max": 0.158001184464, 
                        "mean": 0.016807889938330996, 
                        "min": 0.00671005249023
                    }, 
                    "pypy-nojit": {
                        "max": 0.591130018234, 
                        "mean": 0.4116222620011, 
                        "min": 0.368371009827
                    }
                }, 
                "machine": "922174a8388e0a2f", 
                "platform": "darwin", 
                "timestamp": "20150314070531"
            }, 
            "fannkuch": {
                "engines": {
                    "cpython": {
                        "max": 1.60277795792, 
                        "mean": 1.3217940449724999, 
                        "min": 1.23834490776
                    }, 
                    "d8+pypy": {
                        "max": 16.5829999447, 
                        "mean": 1.7214500069627499, 
                        "min": 0.593000173569
                    }, 
                    "d8+pypy-nojit": {
                        "max": 6.13399982452, 
                        "mean": 5.753799998759999, 
                        "min": 5.49699997902
                    }, 
                    "js+pypy": {
                        "max": 3.15899991989, 
                        "mean": 1.4984500050540002, 
                        "min": 1.27300000191
                    }, 
                    "js+pypy-nojit": {
                        "max": 2.57400012016, 
                        "mean": 2.241200006008, 
                        "min": 2.12800002098
                    }, 
                    "pypy": {
                        "max": 0.270599126816, 
                        "mean": 0.16503483057014998, 
                        "min": 0.144265890121
                    }, 
                    "pypy-nojit": {
                        "max": 1.56933522224, 
                        "mean": 1.2807896614074998, 
                        "min": 1.20620298386
                    }
                }, 
                "machine": "922174a8388e0a2f", 
                "platform": "darwin", 
                "timestamp": "20150314070531"
            }, 
            "float": {
                "engines": {
                    "cpython": {
                        "max": 0.463505983353, 
                        "mean": 0.33549839258195, 
                        "min": 0.310118913651
                    }, 
                    "d8+pypy": {
                        "max": 0.731999874115, 
                        "mean": 0.15740000009530503, 
                        "min": 0.0869998931885
                    }, 
                    "d8+pypy-nojit": {
                        "max": 2.33200001717, 
                        "mean": 1.8517500042915, 
                        "min": 1.72399997711
                    }, 
                    "js+pypy": {
                        "max": 0.328999996185, 
                        "mean": 0.16044999361020001, 
                        "min": 0.139000177383
                    }, 
                    "js+pypy-nojit": {
                        "max": 1.06200003624, 
                        "mean": 0.8315999984741499, 
                        "min": 0.724999904633
                    }, 
                    "pypy": {
                        "max": 0.0817670822144, 
                        "mean": 0.04183156490326499, 
                        "min": 0.0208280086517
                    }, 
                    "pypy-nojit": {
                        "max": 0.784872055054, 
                        "mean": 0.5222139477729499, 
                        "min": 0.47429394722
                    }
                }, 
                "machine": "922174a8388e0a2f", 
                "platform": "darwin", 
                "timestamp": "20150314070531"
            }, 
            "meteor-contest": {
                "engines": {
                    "cpython": {
                        "max": 0.34738111496, 
                        "mean": 0.24663208723074997, 
                        "min": 0.226130962372
                    }, 
                    "d8+pypy": {
                        "max": 12.2409999371, 
                        "mean": 1.4613499999042, 
                        "min": 0.319000005722
                    }, 
                    "d8+pypy-nojit": {
                        "max": 1.72500014305, 
                        "mean": 1.3248999834064998, 
                        "min": 1.24000000954
                    }, 
                    "js+pypy": {
                        "max": 1.97099995613, 
                        "mean": 0.6362500071522501, 
                        "min": 0.447000026703
                    }, 
                    "js+pypy-nojit": {
                        "max": 0.757999897003, 
                        "mean": 0.55169999599455, 
                        "min": 0.509000062943
                    }, 
                    "pypy": {
                        "max": 0.214792013168, 
                        "mean": 0.104590129852335, 
                        "min": 0.0890328884125
                    }, 
                    "pypy-nojit": {
                        "max": 0.513942956924, 
                        "mean": 0.3456351399422001, 
                        "min": 0.325015068054
                    }
                }, 
                "machine": "922174a8388e0a2f", 
                "platform": "darwin", 
                "timestamp": "20150314070531"
            }, 
            "nbody_modified": {
                "engines": {
                    "cpython": {
                        "max": 0.504633903503, 
                        "mean": 0.326573562622, 
                        "min": 0.300070047379
                    }, 
                    "d8+pypy": {
                        "max": 5.80100011826, 
                        "mean": 0.46070001125355003, 
                        "min": 0.166000127792
                    }, 
                    "d8+pypy-nojit": {
                        "max": 3.05100011826, 
                        "mean": 2.7703499913210003, 
                        "min": 2.617000103
                    }, 
                    "js+pypy": {
                        "max": 0.476999998093, 
                        "mean": 0.1572500109672, 
                        "min": 0.128000020981
                    }, 
                    "js+pypy-nojit": {
                        "max": 1.35800004005, 
                        "mean": 1.0942499995225, 
                        "min": 1.01699995995
                    }, 
                    "pypy": {
                        "max": 0.0560040473938, 
                        "mean": 0.023505556583405, 
                        "min": 0.0194058418274
                    }, 
                    "pypy-nojit": {
                        "max": 0.823549985886, 
                        "mean": 0.5965244412422501, 
                        "min": 0.555329799652
                    }
                }, 
                "machine": "922174a8388e0a2f", 
                "platform": "darwin", 
                "timestamp": "20150314070531"
            }, 
            "nqueens": {
                "engines": {
                    "cpython": {
                        "max": 0.385710954666, 
                        "mean": 0.26869183778765, 
                        "min": 0.244299888611
                    }, 
                    "d8+pypy": {
                        "max": 1.90999984741, 
                        "mean": 0.28554999828329997, 
                        "min": 0.170000076294
                    }, 
                    "d8+pypy-nojit": {
                        "max": 1.87400007248, 
                        "mean": 1.5112500071535002, 
                        "min": 1.43099999428
                    }, 
                    "js+pypy": {
                        "max": 0.618999958038, 
                        "mean": 0.34750000238424994, 
                        "min": 0.303999900818
                    }, 
                    "js+pypy-nojit": {
                        "max": 0.868000030518, 
                        "mean": 0.63980000019065, 
                        "min": 0.586999893188
                    }, 
                    "pypy": {
                        "max": 0.0619909763336, 
                        "mean": 0.05051219463348498, 
                        "min": 0.0428941249847
                    }, 
                    "pypy-nojit": {
                        "max": 0.584802865982, 
                        "mean": 0.41229693889615004, 
                        "min": 0.378526210785
                    }
                }, 
                "machine": "922174a8388e0a2f", 
                "platform": "darwin", 
                "timestamp": "20150314070531"
            }, 
            "richards": {
                "engines": {
                    "cpython": {
                        "max": 0.296219110489, 
                        "mean": 0.20493530035024995, 
                        "min": 0.185467004776
                    }, 
                    "d8+pypy": {
                        "max": 60.6540000439, 
                        "mean": 5.690299999710369, 
                        "min": 0.0339999198914
                    }, 
                    "d8+pypy-nojit": {
                        "max": 1.30800008774, 
                        "mean": 1.0550000071528998, 
                        "min": 0.983000040054
                    }, 
                    "js+pypy": {
                        "max": 1.882999897, 
                        "mean": 0.263900005817575, 
                        "min": 0.0840001106262
                    }, 
                    "js+pypy-nojit": {
                        "max": 0.699999809265, 
                        "mean": 0.50915000438685, 
                        "min": 0.457999944687
                    }, 
                    "pypy": {
                        "max": 0.0145289897919, 
                        "mean": 0.005685377120972999, 
                        "min": 0.00395679473877
                    }, 
                    "pypy-nojit": {
                        "max": 0.453469991684, 
                        "mean": 0.29786325693130006, 
                        "min": 0.278641939163
                    }
                }, 
                "machine": "922174a8388e0a2f", 
                "platform": "darwin", 
                "timestamp": "20150314070531"
            }, 
            "spectral-norm": {
                "engines": {
                    "cpython": {
                        "max": 0.38476395607, 
                        "mean": 0.2729475259781501, 
                        "min": 0.244356870651
                    }, 
                    "d8+pypy": {
                        "max": 6.50699996948, 
                        "mean": 0.6637500047684802, 
                        "min": 0.0710000991821
                    }, 
                    "d8+pypy-nojit": {
                        "max": 2.62599992752, 
                        "mean": 2.3064499974245, 
                        "min": 2.16400003433
                    }, 
                    "js+pypy": {
                        "max": 0.558000087738, 
                        "mean": 0.18665000200264997, 
                        "min": 0.116999864578
                    }, 
                    "js+pypy-nojit": {
                        "max": 1.26600003242, 
                        "mean": 0.9863000035290501, 
                        "min": 0.925000190735
                    }, 
                    "pypy": {
                        "max": 0.0776710510254, 
                        "mean": 0.01933543682099, 
                        "min": 0.0139031410217
                    }, 
                    "pypy-nojit": {
                        "max": 0.846710205078, 
                        "mean": 0.6036957025527999, 
                        "min": 0.554473876953
                    }
                }, 
                "machine": "922174a8388e0a2f", 
                "platform": "darwin", 
                "timestamp": "20150314070531"
            }
        }, 
        "geometric_mean": {
            "engines": {
                "cpython": {
                    "max": 0.47302873719181393, 
                    "mean": 0.3323314584154882, 
                    "min": 0.30395895520402894
                }, 
                "d8+pypy": {
                    "max": 6.055368460695305, 
                    "mean": 0.7127537904611667, 
                    "min": 0.12025148576383762
                }, 
                "d8+pypy-nojit": {
                    "max": 2.3388895670046144, 
                    "mean": 1.9587644438774292, 
                    "min": 1.8426947658293662
                }, 
                "js+pypy": {
                    "max": 0.896403785538621, 
                    "mean": 0.29047588688685777, 
                    "min": 0.19118068636775898
                }, 
                "js+pypy-nojit": {
                    "max": 1.0955860845935999, 
                    "mean": 0.8389651688918498, 
                    "min": 0.7719620266952548
                }, 
                "pypy": {
                    "max": 0.08581796892431867, 
                    "mean": 0.03349426545646196, 
                    "min": 0.023139784890765663
                }, 
                "pypy-nojit": {
                    "max": 0.7161630591272171, 
                    "mean": 0.5046782047940007, 
                    "min": 0.46601932759376574
                }
            }, 
            "machine": "922174a8388e0a2f", 
            "platform": "darwin", 
            "timestamp": "20150314070531"
        }
    }, 
    "timestamp": "20150314070531"
}