{
    "bridge": {
        "benchmarks": {
            "regexp": {
                "engines": {
                    "d8+pypy": {
                        "max": 817.55, 
                        "mean": 500.7644749754662, 
                        "min": 375.63829787234044
                    }, 
                    "d8+pypy-nojit": {
                        "max": 373.9519650655022, 
                        "mean": 411.94516450648064, 
                        "min": 441.2043010752688
                    }, 
                    "js+pypy": {
                        "max": 75.72088353413655, 
                        "mean": 99.187915407855, 
                        "min": 95.07843137254902
                    }, 
                    "js+pypy-nojit": {
                        "max": 80.97416974169741, 
                        "mean": 97.47333333333334, 
                        "min": 84.20327868852459
                    }
                }, 
                "machine": "922174a8388e0a2f", 
                "platform": "darwin", 
                "timestamp": "20150307165937"
            }, 
            "sumlog": {
                "engines": {
                    "d8+pypy": {
                        "max": 660.7857091071429, 
                        "mean": 671.8450734323943, 
                        "min": 631.043485973913
                    }, 
                    "d8+pypy-nojit": {
                        "max": 714.4666671766668, 
                        "mean": 827.2666645039998, 
                        "min": 893.4782587956521
                    }, 
                    "js+pypy": {
                        "max": 205.36843099105266, 
                        "mean": 263.7317006180488, 
                        "min": 248.07691574076927
                    }, 
                    "js+pypy-nojit": {
                        "max": 265.650010109, 
                        "mean": 339.5116273748838, 
                        "min": 344.38461523769234
                    }
                }, 
                "machine": "922174a8388e0a2f", 
                "platform": "darwin", 
                "timestamp": "20150307165937"
            }
        }, 
        "geometric_mean": {
            "engines": {
                "d8+pypy": {
                    "max": 735.0002425037319, 
                    "mean": 580.031159044259, 
                    "min": 486.87175000678445
                }, 
                "d8+pypy-nojit": {
                    "max": 516.8909112806248, 
                    "mean": 583.7709329864135, 
                    "min": 627.858623177132
                }, 
                "js+pypy": {
                    "max": 124.70236182471388, 
                    "mean": 161.73743416807616, 
                    "min": 153.57982943203302
                }, 
                "js+pypy-nojit": {
                    "max": 146.6655685921198, 
                    "mean": 181.91572231573198, 
                    "min": 170.28891253660564
                }
            }, 
            "machine": "922174a8388e0a2f", 
            "platform": "darwin", 
            "timestamp": "20150307165937"
        }
    }, 
    "machine": "922174a8388e0a2f", 
    "misc": {
        "benchmarks": {
            "file_size_gz": {
                "engines": {
                    "pypy": {
                        "max": 4146022, 
                        "mean": 4146022.0, 
                        "min": 4146022
                    }, 
                    "pypy-nojit": {
                        "max": 2557788, 
                        "mean": 2557788.0, 
                        "min": 2557788
                    }
                }, 
                "machine": "922174a8388e0a2f", 
                "platform": "darwin", 
                "timestamp": "20150113203542"
            }, 
            "file_size_raw": {
                "engines": {
                    "pypy": {
                        "max": 22067048, 
                        "mean": 22067048.0, 
                        "min": 22067048
                    }, 
                    "pypy-nojit": {
                        "max": 13638890, 
                        "mean": 13638890.0, 
                        "min": 13638890
                    }
                }, 
                "machine": "922174a8388e0a2f", 
                "platform": "darwin", 
                "timestamp": "20150113203542"
            }, 
            "load_time": {
                "engines": {
                    "d8+pypy": {
                        "max": 2.061, 
                        "mean": 2.026, 
                        "min": 2.026
                    }, 
                    "d8+pypy-nojit": {
                        "max": 1.465, 
                        "mean": 1.451, 
                        "min": 1.451
                    }, 
                    "js+pypy": {
                        "max": 2.908, 
                        "mean": 2.665, 
                        "min": 2.665
                    }, 
                    "js+pypy-nojit": {
                        "max": 1.841, 
                        "mean": 1.786, 
                        "min": 1.786
                    }
                }, 
                "machine": "922174a8388e0a2f", 
                "platform": "darwin", 
                "timestamp": "20150113203542"
            }, 
            "pystone": {
                "engines": {
                    "cpython": {
                        "max": 134673.967791, 
                        "mean": 123812.68585650001, 
                        "min": 114293.551558
                    }, 
                    "d8+pypy": {
                        "max": 675674.578499, 
                        "mean": 414743.9262118501, 
                        "min": 17205.781741
                    }, 
                    "d8+pypy-nojit": {
                        "max": 12722.6468662, 
                        "mean": 11495.750589094001, 
                        "min": 7498.50031924
                    }, 
                    "js+pypy": {
                        "max": 467289.228171, 
                        "mean": 373909.09059707995, 
                        "min": 80385.8548015
                    }, 
                    "js+pypy-nojit": {
                        "max": 39215.6760081, 
                        "mean": 37122.10644791, 
                        "min": 36153.2864093
                    }, 
                    "pypy": {
                        "max": 3627663.03408, 
                        "mean": 2699563.3649635, 
                        "min": 929939.028446
                    }, 
                    "pypy-nojit": {
                        "max": 75441.1928701, 
                        "mean": 69311.55150606002, 
                        "min": 67756.7486097
                    }
                }, 
                "machine": "922174a8388e0a2f", 
                "platform": "darwin", 
                "timestamp": "20150113203542"
            }
        }
    }, 
    "platform": "darwin", 
    "py": {
        "benchmarks": {
            "chaos": {
                "engines": {
                    "cpython": {
                        "max": 0.404280900955, 
                        "mean": 0.27834839820854995, 
                        "min": 0.260251045227
                    }, 
                    "d8+pypy": {
                        "max": 2.7460000515, 
                        "mean": 0.35069999694843, 
                        "min": 0.0390000343323
                    }, 
                    "d8+pypy-nojit": {
                        "max": 1.87299990654, 
                        "mean": 1.5617499947540003, 
                        "min": 1.47099995613
                    }, 
                    "js+pypy": {
                        "max": 0.736999988556, 
                        "mean": 0.12390000820162998, 
                        "min": 0.0569999217987
                    }, 
                    "js+pypy-nojit": {
                        "max": 0.90299987793, 
                        "mean": 0.6899500012397499, 
                        "min": 0.638999938965
                    }, 
                    "pypy": {
                        "max": 0.153873920441, 
                        "mean": 0.016648089885736496, 
                        "min": 0.00674986839294
                    }, 
                    "pypy-nojit": {
                        "max": 0.623182058334, 
                        "mean": 0.42952829599385006, 
                        "min": 0.37667798996
                    }
                }, 
                "machine": "922174a8388e0a2f", 
                "platform": "darwin", 
                "timestamp": "20150307165937"
            }, 
            "fannkuch": {
                "engines": {
                    "cpython": {
                        "max": 1.58952498436, 
                        "mean": 1.3315393328665002, 
                        "min": 1.26411700249
                    }, 
                    "d8+pypy": {
                        "max": 16.9709999561, 
                        "mean": 1.7618499994265495, 
                        "min": 0.625999927521
                    }, 
                    "d8+pypy-nojit": {
                        "max": 6.03399991989, 
                        "mean": 5.738999998569499, 
                        "min": 5.56699991226
                    }, 
                    "js+pypy": {
                        "max": 3.42100000381, 
                        "mean": 1.53029999733, 
                        "min": 1.29600000381
                    }, 
                    "js+pypy-nojit": {
                        "max": 2.58100008965, 
                        "mean": 2.3101999998090004, 
                        "min": 2.19099998474
                    }, 
                    "pypy": {
                        "max": 0.233290910721, 
                        "mean": 0.16721389293685002, 
                        "min": 0.148051977158
                    }, 
                    "pypy-nojit": {
                        "max": 1.57542800903, 
                        "mean": 1.2948318362244997, 
                        "min": 1.2214550972
                    }
                }, 
                "machine": "922174a8388e0a2f", 
                "platform": "darwin", 
                "timestamp": "20150307165937"
            }, 
            "float": {
                "engines": {
                    "cpython": {
                        "max": 0.470980167389, 
                        "mean": 0.3515414357186001, 
                        "min": 0.319091081619
                    }, 
                    "d8+pypy": {
                        "max": 0.740000009537, 
                        "mean": 0.15264999866485002, 
                        "min": 0.0859999656677
                    }, 
                    "d8+pypy-nojit": {
                        "max": 2.22000002861, 
                        "mean": 1.9035500049590002, 
                        "min": 1.77999997139
                    }, 
                    "js+pypy": {
                        "max": 0.324000120163, 
                        "mean": 0.16699999570845, 
                        "min": 0.142999887466
                    }, 
                    "js+pypy-nojit": {
                        "max": 1.09500002861, 
                        "mean": 0.837199997902, 
                        "min": 0.770999908447
                    }, 
                    "pypy": {
                        "max": 0.0810949802399, 
                        "mean": 0.03973120450974, 
                        "min": 0.0208840370178
                    }, 
                    "pypy-nojit": {
                        "max": 0.676908016205, 
                        "mean": 0.5366719603539499, 
                        "min": 0.473026037216
                    }
                }, 
                "machine": "922174a8388e0a2f", 
                "platform": "darwin", 
                "timestamp": "20150307165937"
            }, 
            "meteor-contest": {
                "engines": {
                    "cpython": {
                        "max": 0.329849004745, 
                        "mean": 0.24630174636854996, 
                        "min": 0.222616910934
                    }, 
                    "d8+pypy": {
                        "max": 12.6670000553, 
                        "mean": 1.50454999208575, 
                        "min": 0.317999839783
                    }, 
                    "d8+pypy-nojit": {
                        "max": 1.65799999237, 
                        "mean": 1.3251999855035, 
                        "min": 1.2539999485
                    }, 
                    "js+pypy": {
                        "max": 2.29200005531, 
                        "mean": 0.65544999837885, 
                        "min": 0.47200012207
                    }, 
                    "js+pypy-nojit": {
                        "max": 0.791000127792, 
                        "mean": 0.5816500067711, 
                        "min": 0.539000034332
                    }, 
                    "pypy": {
                        "max": 0.161998033524, 
                        "mean": 0.10840821266184002, 
                        "min": 0.091817855835
                    }, 
                    "pypy-nojit": {
                        "max": 0.5006711483, 
                        "mean": 0.3512181282043, 
                        "min": 0.316019058228
                    }
                }, 
                "machine": "922174a8388e0a2f", 
                "platform": "darwin", 
                "timestamp": "20150307165937"
            }, 
            "nbody_modified": {
                "engines": {
                    "cpython": {
                        "max": 0.481856107712, 
                        "mean": 0.3276898980141, 
                        "min": 0.304201841354
                    }, 
                    "d8+pypy": {
                        "max": 5.90700006485, 
                        "mean": 0.4595999956132002, 
                        "min": 0.168999910355
                    }, 
                    "d8+pypy-nojit": {
                        "max": 3.17599987984, 
                        "mean": 2.9005499958980003, 
                        "min": 2.74099993706
                    }, 
                    "js+pypy": {
                        "max": 0.47100019455, 
                        "mean": 0.16435000896449997, 
                        "min": 0.135999917984
                    }, 
                    "js+pypy-nojit": {
                        "max": 1.36999988556, 
                        "mean": 1.102499997616, 
                        "min": 1.03800010681
                    }, 
                    "pypy": {
                        "max": 0.0484058856964, 
                        "mean": 0.023787784576415005, 
                        "min": 0.0196468830109
                    }, 
                    "pypy-nojit": {
                        "max": 0.846019029617, 
                        "mean": 0.6128679037094, 
                        "min": 0.565734863281
                    }
                }, 
                "machine": "922174a8388e0a2f", 
                "platform": "darwin", 
                "timestamp": "20150307165937"
            }, 
            "nqueens": {
                "engines": {
                    "cpython": {
                        "max": 0.374166965485, 
                        "mean": 0.26983478069305, 
                        "min": 0.231717824936
                    }, 
                    "d8+pypy": {
                        "max": 1.68099999428, 
                        "mean": 0.29499999284760003, 
                        "min": 0.172999858856
                    }, 
                    "d8+pypy-nojit": {
                        "max": 1.8630001545, 
                        "mean": 1.5779500007629998, 
                        "min": 1.5
                    }, 
                    "js+pypy": {
                        "max": 0.50200009346, 
                        "mean": 0.35564999580379997, 
                        "min": 0.31200003624
                    }, 
                    "js+pypy-nojit": {
                        "max": 0.881000041962, 
                        "mean": 0.6566999912263, 
                        "min": 0.608000040054
                    }, 
                    "pypy": {
                        "max": 0.0634799003601, 
                        "mean": 0.05218772888183, 
                        "min": 0.0446929931641
                    }, 
                    "pypy-nojit": {
                        "max": 0.604772090912, 
                        "mean": 0.41535615921015, 
                        "min": 0.369776010513
                    }
                }, 
                "machine": "922174a8388e0a2f", 
                "platform": "darwin", 
                "timestamp": "20150307165937"
            }, 
            "richards": {
                "engines": {
                    "cpython": {
                        "max": 0.312912940979, 
                        "mean": 0.21017987728110002, 
                        "min": 0.197390079498
                    }, 
                    "d8+pypy": {
                        "max": 62.0920000076, 
                        "mean": 5.812149989605719, 
                        "min": 0.0329999923706
                    }, 
                    "d8+pypy-nojit": {
                        "max": 1.32399988174, 
                        "mean": 1.0723500132560002, 
                        "min": 1.01399993896
                    }, 
                    "js+pypy": {
                        "max": 2.04099988937, 
                        "mean": 0.2692999958991001, 
                        "min": 0.085000038147
                    }, 
                    "js+pypy-nojit": {
                        "max": 0.758999824524, 
                        "mean": 0.51225000619885, 
                        "min": 0.46799993515
                    }, 
                    "pypy": {
                        "max": 0.0136618614197, 
                        "mean": 0.0055118560791035005, 
                        "min": 0.0040180683136
                    }, 
                    "pypy-nojit": {
                        "max": 0.426751852036, 
                        "mean": 0.3061871528625, 
                        "min": 0.276050806046
                    }
                }, 
                "machine": "922174a8388e0a2f", 
                "platform": "darwin", 
                "timestamp": "20150307165937"
            }, 
            "spectral-norm": {
                "engines": {
                    "cpython": {
                        "max": 0.410701990128, 
                        "mean": 0.27648876905435, 
                        "min": 0.250887870789
                    }, 
                    "d8+pypy": {
                        "max": 6.58000016212, 
                        "mean": 0.67730000019039, 
                        "min": 0.0680000782013
                    }, 
                    "d8+pypy-nojit": {
                        "max": 2.74399995804, 
                        "mean": 2.4602499961855, 
                        "min": 2.33400011063
                    }, 
                    "js+pypy": {
                        "max": 0.573999881744, 
                        "mean": 0.19149999618534996, 
                        "min": 0.112999916077
                    }, 
                    "js+pypy-nojit": {
                        "max": 1.31799983978, 
                        "mean": 1.0261999964706499, 
                        "min": 0.976999998093
                    }, 
                    "pypy": {
                        "max": 0.0595428943634, 
                        "mean": 0.018689966201784997, 
                        "min": 0.0137121677399
                    }, 
                    "pypy-nojit": {
                        "max": 0.816186189651, 
                        "mean": 0.6162935853003, 
                        "min": 0.574450969696
                    }
                }, 
                "machine": "922174a8388e0a2f", 
                "platform": "darwin", 
                "timestamp": "20150307165937"
            }
        }, 
        "geometric_mean": {
            "engines": {
                "cpython": {
                    "max": 0.46830111343582664, 
                    "mean": 0.33662940053839385, 
                    "min": 0.30828142326564
                }, 
                "d8+pypy": {
                    "max": 6.040372392979109, 
                    "mean": 0.72429586167298, 
                    "min": 0.1202790504138516
                }, 
                "d8+pypy-nojit": {
                    "max": 2.3384643145588764, 
                    "mean": 2.016150071899468, 
                    "min": 1.9110027378072252
                }, 
                "js+pypy": {
                    "max": 0.9212075791648011, 
                    "mean": 0.29822064108410345, 
                    "min": 0.1943092387020996
                }, 
                "js+pypy-nojit": {
                    "max": 1.1178022669374692, 
                    "mean": 0.8586224073586743, 
                    "min": 0.8000708712871063
                }, 
                "pypy": {
                    "max": 0.07654733885337134, 
                    "mean": 0.033358570608497805, 
                    "min": 0.0234902942202457
                }, 
                "pypy-nojit": {
                    "max": 0.7024720221590379, 
                    "mean": 0.5161270729858559, 
                    "min": 0.4674982254404607
                }
            }, 
            "machine": "922174a8388e0a2f", 
            "platform": "darwin", 
            "timestamp": "20150307165937"
        }
    }, 
    "timestamp": "20150307165937"
}